Metadata-Version: 1.0
Name: nurzhan-test-2022
Version: 0.0
Summary: Kiwigirim matematikalyk esepter
Home-page: UNKNOWN
Author: UNKNOWN
Author-email: auelbeknurzhan69@gmail.com
License: UNKNOWN
Platform: UNKNOWN
